packetary-0.1.0.dist-info/pbr.json
packetary-0.1.0.dist-info/metadata.json
packetary-0.1.0.dist-info/entry_points.txt
packetary-0.1.0.dist-info/top_level.txt
packetary-0.1.0.dist-info/WHEEL
packetary-0.1.0.dist-info/METADATA
packetary-0.1.0.dist-info/DESCRIPTION.rst
packetary-0.1.0.dist-info/RECORD
packetary/api.py
packetary/__init__.py
packetary/schemas/rpm_repo_schema.py
packetary/schemas/package_files_schema.py
packetary/schemas/__init__.py
packetary/schemas/packages_schema.py
packetary/schemas/deb_repo_schema.py
packetary/objects/repository.py
packetary/objects/base.py
packetary/objects/statistics.py
packetary/objects/packages_forest.py
packetary/objects/packages_tree.py
packetary/objects/package_version.py
packetary/objects/package.py
packetary/objects/index.py
packetary/objects/__init__.py
packetary/objects/package_relation.py
packetary/drivers/base.py
packetary/drivers/rpm_driver.py
packetary/drivers/deb_driver.py
packetary/drivers/__init__.py
packetary/controllers/repository.py
packetary/controllers/__init__.py
packetary/tests/test_deb_driver.py
packetary/tests/test_schemas.py
packetary/tests/test_streams.py
packetary/tests/test_library_utils.py
packetary/tests/test_rpm_driver.py
packetary/tests/test_connections.py
packetary/tests/base.py
packetary/tests/test_command_utils.py
packetary/tests/test_cli_commands.py
packetary/tests/test_repository_api.py
packetary/tests/test_index.py
packetary/tests/test_executor.py
packetary/tests/test_objects.py
packetary/tests/test_repository_contoller.py
packetary/tests/__init__.py
packetary/tests/test_checksums.py
packetary/tests/test_packages_tree.py
packetary/tests/test_packages_forest.py
packetary/tests/stubs/executor.py
packetary/tests/stubs/generator.py
packetary/tests/stubs/__init__.py
packetary/tests/stubs/helpers.py
packetary/tests/data/groups.xml
packetary/tests/data/repomd2.xml
packetary/tests/data/Release
packetary/tests/data/repomd.xml
packetary/tests/data/Packages
packetary/tests/data/primary.xml
packetary/library/utils.py
packetary/library/executor.py
packetary/library/checksum.py
packetary/library/__init__.py
packetary/library/connections.py
packetary/library/streams.py
packetary/cli/__init__.py
packetary/cli/app.py
